track_id_generator_nan/__init__.py
track_id_generator_nan/generate.py
track_id_generator_nan-0.0.1.dist-info/LICENSE
track_id_generator_nan-0.0.1.dist-info/METADATA
track_id_generator_nan-0.0.1.dist-info/WHEEL
track_id_generator_nan-0.0.1.dist-info/top_level.txt
track_id_generator_nan-0.0.1.dist-info/RECORD
