Metadata-Version: 2.1
Name: track_id_generator_nan
Version: 0.0.1
Summary: To generate a unique 12 track id, which contain letters and digits.
Home-page: https://github.com/nan-wang-good/generate_pkg.git
Author: Nan
Author-email: nancybetter4work@gmail.com
Classifier: Programming Language :: Python :: 3
Classifier: License :: OSI Approved :: MIT License
Classifier: Operating System :: OS Independent
Requires-Python: >=3.6
License-File: LICENSE
